nadeo_api/__init__.py
nadeo_api/auth.py
nadeo_api/config.py
nadeo_api/core.py
nadeo_api/live.py
nadeo_api/meet.py
nadeo_api/oauth.py
nadeo_api/util.py
nadeo_api-0.7.0.dist-info/licenses/LICENSE.txt
nadeo_api-0.7.0.dist-info/METADATA
nadeo_api-0.7.0.dist-info/WHEEL
nadeo_api-0.7.0.dist-info/top_level.txt
nadeo_api-0.7.0.dist-info/RECORD
