Metadata-Version: 2.4
Name: nadeo-api
Version: 0.7.0
Summary: Access Nadeo's web services API and the public Trackmania API
Author-email: Ezio416 <e@e416.dev>
License-Expression: MIT
Project-URL: Bug Tracker, https://github.com/ezio416/py-nadeo-api/issues
Project-URL: Documentation, https://nadeo-api.readthedocs.io/en/latest/
Project-URL: Repository, https://github.com/ezio416/py-nadeo-api
Keywords: nadeo,api,trackmania
Classifier: Programming Language :: Python :: 3
Classifier: Operating System :: OS Independent
Requires-Python: >=3.12
License-File: LICENSE.txt
Requires-Dist: requests>=2.31.0
Dynamic: license-file
